<?xml version="1.0" encoding="utf-8"?>
<SoundOptions xmlns:xsi="http://www.w3.org/2001/XMLSchema-instance" xmlns:xsd="http://www.w3.org/2001/XMLSchema">
  <SoundOptionsRefueled>
    <VaryFrequency>true</VaryFrequency>
    <Activated>true</Activated>
    <SoundOptions>
      <SoundOption>
        <SoundPath>\Sounds\Actions\GO.wav</SoundPath>
        <SpecialSound>0</SpecialSound>
      </SoundOption>
      <SoundOption>
        <SpecialSound>1</SpecialSound>
      </SoundOption>
    </SoundOptions>
  </SoundOptionsRefueled>
  <SoundOptionsDisqualified>
    <VaryFrequency>true</VaryFrequency>
    <Activated>true</Activated>
    <SoundOptions>
      <SoundOption>
        <SoundPath>\Sounds\Actions\IstDisqualifiziert.wav</SoundPath>
        <SpecialSound>1</SpecialSound>
      </SoundOption>
    </SoundOptions>
  </SoundOptionsDisqualified>
  <SoundOptionsFalseStart>
    <VaryFrequency>true</VaryFrequency>
    <Activated>true</Activated>
    <SoundOptions>
      <SoundOption>
        <SoundPath>\Sounds\Actions\FehlstartVon.wav</SoundPath>
        <SpecialSound>0</SpecialSound>
      </SoundOption>
      <SoundOption>
        <SpecialSound>1</SpecialSound>
      </SoundOption>
    </SoundOptions>
  </SoundOptionsFalseStart>
  <SoundOptionsLapDetectedNotAdded>
    <VaryFrequency>true</VaryFrequency>
    <Activated>true</Activated>
    <SoundOptions>
      <SoundOption>
        <SoundPath>\Sounds\Actions\RundeVon.wav</SoundPath>
        <SpecialSound>0</SpecialSound>
      </SoundOption>
      <SoundOption>
        <SpecialSound>1</SpecialSound>
      </SoundOption>
      <SoundOption>
        <SoundPath>\Sounds\Actions\NichtGez채hlt.wav</SoundPath>
        <SpecialSound>0</SpecialSound>
      </SoundOption>
    </SoundOptions>
  </SoundOptionsLapDetectedNotAdded>
  <SoundOptionsNoFuel>
    <VaryFrequency>true</VaryFrequency>
    <Activated>true</Activated>
    <SoundOptions>
      <SoundOption>
        <SoundPath>\Sounds\Actions\KeinSpritF체r.wav</SoundPath>
        <SpecialSound>0</SpecialSound>
      </SoundOption>
      <SoundOption>
        <SpecialSound>1</SpecialSound>
      </SoundOption>
    </SoundOptions>
  </SoundOptionsNoFuel>
  <SoundOptionsLowFuel>
    <VaryFrequency>true</VaryFrequency>
    <Activated>true</Activated>
    <SoundOptions>
      <SoundOption>
        <SoundPath>\Sounds\Actions\WenigSpritF체r.wav</SoundPath>
        <SpecialSound>0</SpecialSound>
      </SoundOption>
      <SoundOption>
        <SpecialSound>1</SpecialSound>
      </SoundOption>
    </SoundOptions>
  </SoundOptionsLowFuel>
  <SoundOptionsPitOut>
    <VaryFrequency>true</VaryFrequency>
    <Activated>false</Activated>
    <SoundOptions />
  </SoundOptionsPitOut>
  <SoundOptionsPitIn>
    <VaryFrequency>true</VaryFrequency>
    <Activated>true</Activated>
    <SoundOptions>
      <SoundOption>
        <SoundPath>\Sounds\Actions\PitstopVon.wav</SoundPath>
        <SpecialSound>0</SpecialSound>
      </SoundOption>
      <SoundOption>
        <SpecialSound>1</SpecialSound>
      </SoundOption>
    </SoundOptions>
  </SoundOptionsPitIn>
  <SoundOptionsLap>
    <VaryFrequency>true</VaryFrequency>
    <Activated>true</Activated>
    <SoundOptions>
      <SoundOption>
        <SpecialSound>1</SpecialSound>
      </SoundOption>
      <SoundOption>
        <SpecialSound>2</SpecialSound>
      </SoundOption>
    </SoundOptions>
  </SoundOptionsLap>
  <SoundOptionsPenalty>
    <VaryFrequency>true</VaryFrequency>
    <Activated>true</Activated>
    <SoundOptions>
      <SoundOption>
        <SoundPath>\Sounds\Actions\StrafeF체r.wav</SoundPath>
        <SpecialSound>0</SpecialSound>
      </SoundOption>
      <SoundOption>
        <SpecialSound>1</SpecialSound>
      </SoundOption>
    </SoundOptions>
  </SoundOptionsPenalty>
</SoundOptions>